setup.py
faers/__init__.py
faers.egg-info/PKG-INFO
faers.egg-info/SOURCES.txt
faers.egg-info/dependency_links.txt
faers.egg-info/not-zip-safe
faers.egg-info/requires.txt
faers.egg-info/top_level.txt