Metadata-Version: 1.0
Name: faers
Version: 0.1
Summary: Tools for workding with data from the FDA Adverse Event Reporting System.
Home-page: http://github.com/mlbernauer/faers
Author: Michael L. Bernauer
Author-email: mlbernauer@gmail.com
License: MIT
Platform: UNKNOWN
